apys/__init__.py
apys/apiobject.py
apys/commandline.py
apys/config.py
apys/log.py
apys/project.py
apys/routes.py
apys/server.py
apys/settings.py
apys-3.2.1.dist-info/LICENSE.txt
apys-3.2.1.dist-info/METADATA
apys-3.2.1.dist-info/WHEEL
apys-3.2.1.dist-info/entry_points.txt
apys-3.2.1.dist-info/top_level.txt
apys-3.2.1.dist-info/RECORD
