Metadata-Version: 2.1
Name: apys
Version: 3.2.1
Summary: A simple back-end rest framework in python using aiohttp lib
Home-page: https://github.com/seijihirao/apys
Author: Rodrigo Seiji Piubeli Hirao
Author-email: rodrigo.seiji.hirao@gmail.com
License: MIT
Keywords: backend rest web service
Platform: UNKNOWN
Classifier: Development Status :: 4 - Beta
Classifier: Intended Audience :: Developers
Classifier: Topic :: Software Development :: Libraries :: Application Frameworks
Classifier: License :: OSI Approved :: MIT License
Classifier: Programming Language :: Python :: 3
Classifier: Programming Language :: Python :: 3.4
Classifier: Programming Language :: Python :: 3.5
Classifier: Programming Language :: Python :: 3.6
Classifier: Programming Language :: Python :: 3.7
Requires-Dist: aiohttp
Requires-Dist: aiohttp-cors
